MANIFEST.in
README.md
VERSION
git_version.py
requirements.txt
setup.py
neptune_lib.egg-info/PKG-INFO
neptune_lib.egg-info/SOURCES.txt
neptune_lib.egg-info/dependency_links.txt
neptune_lib.egg-info/requires.txt
neptune_lib.egg-info/top_level.txt
neptunelib/__init__.py
neptunelib/client.py
neptunelib/credentials.py
neptunelib/exceptions.py
neptunelib/experiment.py
neptunelib/model.py
neptunelib/oauth.py
neptunelib/project.py
neptunelib/session.py
neptunelib/utils.py