Metadata-Version: 1.0
Name: neptune-lib
Version: 0.1.2
Summary: Neptune Python library
Home-page: https://neptune.ml/
Author: neptune.ml
Author-email: contact@neptune.ml
License: Apache License 2.0
Platform: UNKNOWN
